[{
	"raw": {},
	"required": [
		"Filename",
		"Size"
	],
	"package": "libvdjtools-java",
	"source": "vdjtools",
	"version": "1.2.1+git20190311+repack-2",
	"section": "non-free/science",
	"priority": "optional",
	"architecture": "all",
	"depends": [
		"groovy",
		"libcommons-cli-java",
		"libcommons-lang3-java",
		"libcommons-math3-java",
		"libmilib-java"
	],
	"installedSize": 1208,
	"maintainer": "Debian Med Packaging Team <debian-med-packaging@lists.alioth.debian.org>",
	"description": "Java library of vdjtools",
	"homepage": "https://github.com/mikessh/vdjtools",
	"filename": "pool/non-free/v/vdjtools/libvdjtools-java_1.2.1+git20190311+repack-2_all.deb",
	"size": 1069152,
	"md5": "346c40569f03e68ffff403d97e7a29db",
	"sha256": "06831699ac26c9fc80abf09a6d963275dd18e69d52d8a59f0d1d74371e9f9739",
	"descriptionMd5": "7e9969d6b00277d3bd7ca29f1a863e71"
}]