[{"raw":{},"required":["Filename","Size"],"package":"firefox-l10n-mr","source":"firefox","version":"128.0.3-2","section":"localization","priority":"optional","architecture":"all","depends":["firefox (>= 128.0.3-2)","firefox (<< 128.0.3-2.1~)"],"installedSize":589,"maintainer":"Maintainers of Mozilla-related packages <team+pkg-mozilla@tracker.debian.org>","description":"Marathi language package for Firefox","filename":"pool/main/f/firefox/firefox-l10n-mr_128.0.3-2_all.deb","size":453636,"md5":"2a8126531725f7dc0d6840f165688fd2","sha256":"918782ba06f2a8f36c4a1f046ec911c0f3ebf193b0122314cefca4b66604a299","descriptionMd5":"12c5ce56a949a787653c19082598bced"}]