{"raw":{},"required":["Filename","Size"],"package":"g++-mipsel-linux-gnu","source":"gcc-defaults-mipsen (1.203)","version":"4:12.2.0-4","section":"devel","priority":"optional","architecture":"amd64","depends":["cpp-mipsel-linux-gnu (= 4:12.2.0-4)","gcc-mipsel-linux-gnu (= 4:12.2.0-4)","g++-12-mipsel-linux-gnu (>= 12.2.0-1~)"],"installedSize":11,"maintainer":"Debian GCC Maintainers <debian-gcc@lists.debian.org>","description":"GNU C++ compiler for the mipsel architecture","filename":"pool/main/g/gcc-defaults-mipsen/g++-mipsel-linux-gnu_12.2.0-4_amd64.deb","size":1176,"md5":"6b70c12d2d0afe3df4f09cfc3aea9667","sha256":"9ef89e696680bed527ad3089d74bc874ca337d40da5f0486fff295660884989a","descriptionMd5":"a78509f9da485fd866d51fcfdb80a191"}