[{"raw":{},"required":["Filename","Size"],"package":"libastro-fits-cfitsio-perl","source":"libastro-fits-cfitsio-perl (1.18-1)","version":"1.18-1+b3","section":"perl","priority":"optional","architecture":"amd64","depends":["perl (>= 5.40.0-6)","perlapi-5.40.0","libc6 (>= 2.14)","libcfitsio10t64 (>= 4.3.0)"],"installedSize":1200,"maintainer":"Debian Perl Group <pkg-perl-maintainers@lists.alioth.debian.org>","description":"Perl extension for using the cfitsio library","homepage":"https://metacpan.org/release/Astro-FITS-CFITSIO","filename":"pool/main/liba/libastro-fits-cfitsio-perl/libastro-fits-cfitsio-perl_1.18-1+b3_amd64.deb","size":404728,"md5":"05efe71ab568a08e828ce66643f10dfb","sha256":"20b1db6e4b790f1bfb64616d24f2f954c0eb2b487e210bccf1c96946b510a8b7","descriptionMd5":"c59bd528b4196e31e9778e4b93fe8787"}]