[{
	"raw": {},
	"required": [
		"Filename",
		"Size"
	],
	"package": "liblogs-ocaml",
	"source": "ocaml-logs (0.10.0-1)",
	"version": "0.10.0-1+b8",
	"section": "ocaml",
	"priority": "optional",
	"architecture": "amd64",
	"depends": [
		"libfmt-ocaml-35kg8",
		"libjs-of-ocaml-xa0y6",
		"liblwt-ocaml-0ubd5",
		"libstdlib-ocaml-1ltp0",
		"ocaml-base-5.4.1"
	],
	"suggests": [
		"ocaml-findlib"
	],
	"installedSize": 353,
	"maintainer": "Debian OCaml Maintainers <debian-ocaml-maint@lists.debian.org>",
	"description": "logging infrastructure for OCaml (runtime)",
	"homepage": "https://erratique.ch/software/logs",
	"filename": "pool/main/o/ocaml-logs/liblogs-ocaml_0.10.0-1+b8_amd64.deb",
	"size": 81292,
	"md5": "ac4df53012c01be506c21b3aefcee120",
	"sha256": "9cac679f165aeffa4e9f49c3322e5654ded7f47902dca791733859d1ee365876",
	"descriptionMd5": "0c304d192500aec1626644a68e65d2ea"
}]