[{"raw":{},"required":["Filename","Size"],"package":"xmms2-plugin-html","source":"xmms2 (0.8+dfsg-28)","version":"0.8+dfsg-28+b1","section":"sound","priority":"optional","architecture":"amd64","depends":["xmms2-core (= 0.8+dfsg-28+b1)","libc6 (>= 2.4)","libglib2.0-0t64 (>= 2.12.0)"],"enhances":["xmms2-core"],"installedSize":45,"maintainer":"Debian QA Group <packages@qa.debian.org>","description":"XMMS2 - HTML playlist plug-in","filename":"pool/main/x/xmms2/xmms2-plugin-html_0.8+dfsg-28+b1_amd64.deb","size":11788,"md5":"2bd448dc22ac8aa66f6455e56b6eb0f6","sha256":"de8a9815a8fb16a701fbf0cf765ad8eb54267f5b598528bea90f5c732715e08b","descriptionMd5":"40b573a57b050a76e3704848c97d49e6"}]