[{
	"raw": {},
	"required": [
		"Filename",
		"Size"
	],
	"package": "libatlas-cpp-doc",
	"source": "atlas-cpp",
	"version": "0.6.4-2",
	"section": "doc",
	"priority": "optional",
	"architecture": "all",
	"suggests": [
		"libatlas-cpp-0.6-dev (>= 0.6.4-2)"
	],
	"installedSize": 10408,
	"maintainer": "Debian Games Team <pkg-games-devel@lists.alioth.debian.org>",
	"description": "World Forge wire protocol library - documentation",
	"homepage": "https://www.worldforge.org/",
	"filename": "pool/main/a/atlas-cpp/libatlas-cpp-doc_0.6.4-2_all.deb",
	"size": 446260,
	"md5": "94908b5e75a47dfc373edf1e9b457b4e",
	"sha256": "88e2cc45875b87df8ae4f098e241715f4f23328df89bd3ca12721cdba43e098a",
	"descriptionMd5": "86f19dfde37deb75d033e975ff127118"
}]