{"raw":{},"required":["Filename","Size"],"package":"libghc-bindings-nettle-doc","source":"haskell-bindings-nettle","version":"0.4-2","section":"doc","priority":"optional","architecture":"all","depends":["haddock-interface-33"],"recommends":["ghc-doc","libjs-mathjax"],"installedSize":1354,"maintainer":"Debian Haskell Group <pkg-haskell-maintainers@lists.alioth.debian.org>","description":"Haskell bindings to nettle crypto library; documentation","homepage":"http://floss.scru.org/bindings-nettle","filename":"pool/main/h/haskell-bindings-nettle/libghc-bindings-nettle-doc_0.4-2_all.deb","size":69188,"md5":"6ee01507a073505248780449679acda3","sha256":"9810ab4a6cf2aaaa4d5842aa7c0e3291a33751928ca41ea4355d28b8fc74f79e","descriptionMd5":"0d2c51461afea03a18d604b55023d98f"}