[{"raw":{},"required":["Filename","Size"],"package":"libmono-system-web-extensions-design4.0-cil","source":"mono","version":"5.18.0.240+dfsg-3","section":"cli-mono","priority":"optional","architecture":"all","depends":["libmono-corlib4.5-cil (>= 5.18.0.240)","libmono-system-design4.0-cil (>= 5.16.0.220)","libmono-system4.0-cil (>= 5.18.0.240)"],"installedSize":97,"maintainer":"Debian Mono Group <pkg-mono-group@lists.alioth.debian.org>","description":"Mono System.Web.Extensions.Design library (for CLI 4.0)","homepage":"http://www.mono-project.com/","filename":"pool/main/m/mono/libmono-system-web-extensions-design4.0-cil_5.18.0.240+dfsg-3_all.deb","size":39396,"md5":"a144e011f51d8f4bf99bec39c455515c","sha256":"786ecd24cb4d04b34346264e27db4053365d80d61a25688bb77646d192c2cbdb","descriptionMd5":"6b16bd81d976bf77288d30d485a7e675"}]