{"raw":{},"required":["Filename","Size"],"package":"node-acorn-dynamic-import","version":"3.0.0-1","section":"javascript","priority":"optional","architecture":"all","depends":["node-acorn (>= 4.0.3)","nodejs"],"installedSize":22,"maintainer":"Debian Javascript Maintainers <pkg-javascript-devel@lists.alioth.debian.org>","description":"Support dynamic imports in acorn","homepage":"https://github.com/kesne/acorn-dynamic-import","filename":"pool/main/n/node-acorn-dynamic-import/node-acorn-dynamic-import_3.0.0-1_all.deb","size":5216,"md5":"3cced317d81f59228b55703cffd2bde1","sha256":"4ef8c3a9adc4d2e91229ac23ffa6182b1d95d1b4e6051dba73f528b36412ed02","descriptionMd5":"8070a8200aac1555042bdbe008bf8511"}