[{"raw":{},"required":["Filename","Size"],"package":"python3-imageio","source":"python-imageio","version":"2.4.1-2","section":"python","priority":"optional","architecture":"all","depends":["python3-numpy","python3-pil","python3:any"],"suggests":["python-imageio-doc","python3-astropy","python3-gdal","ffmpeg"],"installedSize":4286,"maintainer":"Debian Science Maintainers <debian-science-maintainers@lists.alioth.debian.org>","description":"library for reading and writing image data (Python 3)","homepage":"http://imageio.github.io/","filename":"pool/main/p/python-imageio/python3-imageio_2.4.1-2_all.deb","size":3136916,"md5":"369da3510116d6bd5b68896a04e1f0e7","sha256":"cbe44651af0994f5f7ec96bc84e290087a9ade2b341d93386db45f88d6c49c44","descriptionMd5":"75ff5eb88d8663e92e4685e27c8e1187"}]