[{
	"raw": {},
	"required": [
		"Filename",
		"Size"
	],
	"package": "qtwebview5-doc",
	"source": "qtwebview-opensource-src",
	"version": "5.11.3-2",
	"section": "doc",
	"priority": "optional",
	"architecture": "all",
	"installedSize": 170,
	"maintainer": "Debian Qt/KDE Maintainers <debian-qt-kde@lists.debian.org>",
	"description": "display web content in a QML application - Documentation",
	"homepage": "https://doc.qt.io/qt-5/qtwebview-index.html",
	"filename": "pool/main/q/qtwebview-opensource-src/qtwebview5-doc_5.11.3-2_all.deb",
	"size": 89764,
	"md5": "2244f01a3d40a05377ef05fb824bb86a",
	"sha256": "f5fb6853d07f0cace0016ade161c2368e86ee4780a3f1c10f5abf79ff546b4e3",
	"descriptionMd5": "9ee3d8a2835e39c1b1190138ab520ef4"
}]