{
	"raw": {},
	"required": [
		"Filename",
		"Size"
	],
	"package": "developers-reference-it",
	"source": "developers-reference",
	"version": "11.0.21",
	"section": "doc",
	"priority": "optional",
	"architecture": "all",
	"recommends": [
		"debian-policy",
		"developers-reference",
		"libjs-sphinxdoc (>= 2.0)"
	],
	"suggests": [
		"doc-base"
	],
	"installedSize": 1640,
	"maintainer": "Developers Reference Maintainers <debian-policy@lists.debian.org>",
	"description": "guidelines and information for Debian developers, in Italian",
	"homepage": "https://www.debian.org/doc/devel-manuals#devref",
	"filename": "pool/main/d/developers-reference/developers-reference-it_11.0.21_all.deb",
	"size": 677328,
	"md5": "61922f451aba1adf4a1412560df3d42e",
	"sha256": "4f9e0dd6500f22a35cd9db5a8693c400f57585d22119ed26a5c1fcc3bcaf50cd",
	"descriptionMd5": "e6588f4749e7d8ae4657e7d9b10d589b"
}