{
	"raw": {},
	"required": [
		"Filename",
		"Size"
	],
	"package": "python3-logbook",
	"source": "logbook (1.5.3-4)",
	"version": "1.5.3-4+b1",
	"section": "python",
	"priority": "optional",
	"architecture": "amd64",
	"depends": [
		"python3 (<< 3.10)",
		"python3 (>= 3.9~)",
		"python3:any",
		"libc6 (>= 2.14)"
	],
	"suggests": [
		"python-logbook-doc"
	],
	"installedSize": 407,
	"maintainer": "Agustin Henze <tin@debian.org>",
	"description": "logging system for Python that replaces the standard library's module (Python3)",
	"homepage": "http://pythonhosted.org/Logbook/",
	"filename": "pool/main/l/logbook/python3-logbook_1.5.3-4+b1_amd64.deb",
	"size": 100544,
	"md5": "f79a33330d0c67ef40550da015182f41",
	"sha256": "e99a455c84cc133ddf33899f8eedf9dfb235442aea19390a49f79f25d03009f1",
	"descriptionMd5": "21cb5e7264a342440fec92ca69b94f59"
}