{"raw":{},"required":["Filename","Size"],"package":"ruby-strptime","source":"ruby-strptime (0.2.5-1)","version":"0.2.5-1+b1","section":"ruby","priority":"optional","architecture":"amd64","depends":["ruby:any","libc6 (>= 2.17)","libruby2.7 (>= 2.7.0)","ruby (>= 1:2.7~0)","ruby (<< 1:2.8~)"],"installedSize":63,"maintainer":"Debian Ruby Extras Maintainers <pkg-ruby-extras-maintainers@lists.alioth.debian.org>","description":"fast strptime/strftime engine","homepage":"https://github.com/nurse/strptime","filename":"pool/main/r/ruby-strptime/ruby-strptime_0.2.5-1+b1_amd64.deb","size":14600,"md5":"86a9a5c40bc4b519350a0606a8886aa9","sha256":"1eee51d3e61e43428f06d51c94c16fa4df56e53d75e21af85afd35af868472b2","descriptionMd5":"898d96432aecdb7cf8a51ab3764bc892"}