{
	"raw": {},
	"required": [
		"Filename",
		"Size"
	],
	"package": "dot2tex",
	"version": "2.12.0-1",
	"section": "graphics",
	"priority": "optional",
	"architecture": "all",
	"depends": [
		"graphviz",
		"python3-pyparsing",
		"python3-setuptools",
		"python3:any",
		"libjs-sphinxdoc (>= 9.0)"
	],
	"recommends": [
		"preview-latex-style",
		"texlive-latex-base",
		"texlive-latex-extra",
		"texlive-pictures",
		"texlive-pstricks"
	],
	"enhances": [
		"latex-beamer"
	],
	"installedSize": 828,
	"maintainer": "Debian Python Team <team+python@tracker.debian.org>",
	"description": "Graphviz to LaTeX converter",
	"homepage": "https://github.com/sagemath/dot2tex",
	"filename": "pool/main/d/dot2tex/dot2tex_2.12.0-1_all.deb",
	"size": 333488,
	"md5": "66e7f3fb7383298b1a046423fbf8b0fe",
	"sha256": "d1b7516a2768c9f516d7ceb4a09b185bbbf9fefdf26b72edcff38bbdd579c18f",
	"descriptionMd5": "ed8cebc8844f9f26ab1b3ee36557dcfc"
}