{
	"raw": {},
	"required": [
		"Filename",
		"Size"
	],
	"package": "dxvk-wine64-development",
	"source": "dxvk",
	"version": "2.6-1",
	"section": "libs",
	"priority": "optional",
	"architecture": "amd64",
	"depends": [
		"dxvk-wine64"
	],
	"installedSize": 20,
	"maintainer": "Alexandre Viau <aviau@debian.org>",
	"description": "transitional package",
	"homepage": "https://github.com/doitsujin/dxvk",
	"filename": "pool/main/d/dxvk/dxvk-wine64-development_2.6-1_amd64.deb",
	"size": 7440,
	"md5": "d782b7db03a27b955da8c1253ab0ff6a",
	"sha256": "aec42bc716cab9242f3a97873e7c1370afab5fadc00ab42f6eb95b97fe60a62e",
	"descriptionMd5": "bfe8ebc058cce6653c20fea6f85a4246"
}