{
	"raw": {},
	"required": [
		"Filename",
		"Size"
	],
	"package": "firefox-l10n-hsb",
	"source": "firefox",
	"version": "145.0.1-1",
	"section": "localization",
	"priority": "optional",
	"architecture": "all",
	"depends": [
		"firefox (>= 145.0.1-1)",
		"firefox (<< 145.0.1-1.1~)"
	],
	"installedSize": 522,
	"maintainer": "Maintainers of Mozilla-related packages <team+pkg-mozilla@tracker.debian.org>",
	"description": "Upper Sorbian language package for Firefox",
	"filename": "pool/main/f/firefox/firefox-l10n-hsb_145.0.1-1_all.deb",
	"size": 409036,
	"md5": "b4cd79c327493649bdc4f6f4dd6c45be",
	"sha256": "65a0c4cfa2822b8313d08bc2142568f79e54bee09a324d35f8e733c4491ee231",
	"descriptionMd5": "cbccb57ca818889ace4294a2a8bf1648"
}