{"raw":{},"required":["Filename","Size"],"package":"firefox-l10n-hu","source":"firefox","version":"130.0.1-1","section":"localization","priority":"optional","architecture":"all","depends":["firefox (>= 130.0.1-1)","firefox (<< 130.0.1-1.1~)"],"recommends":["hunspell-hu | myspell-hu"],"installedSize":712,"maintainer":"Maintainers of Mozilla-related packages <team+pkg-mozilla@tracker.debian.org>","description":"Hungarian language package for Firefox","filename":"pool/main/f/firefox/firefox-l10n-hu_130.0.1-1_all.deb","size":588864,"md5":"da5280ab03a67e03e8ce0c67fa910053","sha256":"6b75f296340dcdc8a89dcabebcf3fdc71d7560779de0d5a35115bbc011b2b754","descriptionMd5":"1e820bc032f206c675df3d2eecbf8419"}