{
	"raw": {},
	"required": [
		"Filename",
		"Size"
	],
	"package": "g++-13",
	"source": "gcc-13",
	"version": "13.4.0-8",
	"section": "devel",
	"priority": "optional",
	"architecture": "amd64",
	"depends": [
		"g++-13-x86-64-linux-gnu (= 13.4.0-8)",
		"gcc-13-base (= 13.4.0-8)",
		"gcc-13 (= 13.4.0-8)"
	],
	"suggests": [
		"g++-13-multilib",
		"gcc-13-doc (>= 13)"
	],
	"installedSize": 34,
	"maintainer": "Debian GCC Maintainers <debian-gcc@lists.debian.org>",
	"description": "GNU C++ compiler",
	"homepage": "http://gcc.gnu.org/",
	"filename": "pool/main/g/gcc-13/g++-13_13.4.0-8_amd64.deb",
	"size": 20660,
	"md5": "9b9fc36471d6b2d6e1fed3937930a52b",
	"sha256": "b6d197228399265c7cb9f0f17d3117470f6247a6e14305d8560c1f8620081e8a",
	"descriptionMd5": "0a3fad3367cb994bd16c61b0e16a8b9c"
}