{
	"raw": {},
	"required": [
		"Filename",
		"Size"
	],
	"package": "libmysql++3t64",
	"source": "mysql++ (3.2.5-2.3)",
	"version": "3.2.5-2.3+b2",
	"section": "libs",
	"priority": "optional",
	"architecture": "amd64",
	"depends": [
		"libc6 (>= 2.38)",
		"libgcc-s1 (>= 3.0)",
		"libmariadb3 (>= 3.0.0)",
		"libstdc++6 (>= 13.1)"
	],
	"replaces": [
		"libmysql++3",
		"libmysql++3v5"
	],
	"breaks": [
		"libmysql++3v5 (<< 3.2.5-2.3)"
	],
	"conflicts": [
		"libmysql++3"
	],
	"installedSize": 422,
	"maintainer": "Athena Capital Research <acr-debian@athenacr.com>",
	"description": "MySQL C++ library bindings (runtime)",
	"homepage": "https://tangentsoft.net/mysqlpp/",
	"filename": "pool/main/m/mysql++/libmysql++3t64_3.2.5-2.3+b2_amd64.deb",
	"size": 158380,
	"md5": "cb8a7b834264b80d1c4d5e5ac60f600c",
	"sha256": "3511026305d2228dd4230d98e3f5d2b63abd1c32d18ace80b3ec716427c8d2b1",
	"descriptionMd5": "1fb45f774499d200041215cee05918a3"
}