{"raw":{},"required":["Filename","Size"],"package":"libubootenv-tool","source":"libubootenv (0.3.5-0.1)","version":"0.3.5-0.1+b2","section":"utils","priority":"optional","architecture":"amd64","depends":["libc6 (>= 2.34)","libubootenv0.1 (= 0.3.5-0.1+b2)"],"conflicts":["u-boot-tools (<< 2019.10)"],"installedSize":33,"maintainer":"Nobuhiro Iwamatsu <iwamatsu@debian.org>","description":"Library to access U-Boot environment - tool","homepage":"https://github.com/sbabic/libubootenv","filename":"pool/main/libu/libubootenv/libubootenv-tool_0.3.5-0.1+b2_amd64.deb","size":8672,"md5":"8be5a8b8e52fa1800c71cf4aec805b5d","sha256":"cced582480fc7ee77c324dde40d5eb5a70f41e6e125c9e58bd386d22cdd0a56b","descriptionMd5":"ea6458eb937ff87fe1ea9e379b6a3e6c"}