{
	"raw": {},
	"required": [
		"Filename",
		"Size"
	],
	"package": "mlton-basis",
	"source": "mlton",
	"version": "20241230+git20251029+dfsg-4",
	"section": "devel",
	"priority": "optional",
	"architecture": "amd64",
	"installedSize": 8944,
	"maintainer": "Ryan Kavanagh <rak@debian.org>",
	"description": "Optimizing compiler for Standard ML - basis library",
	"homepage": "http://mlton.org/",
	"filename": "pool/main/m/mlton/mlton-basis_20241230+git20251029+dfsg-4_amd64.deb",
	"size": 1089536,
	"md5": "357b9627ff689c20107fb4c179fd4b9b",
	"sha256": "cb90bce0c1a03f63d32c73fecc9cdcfc9932b3c1d52ce863b2c119d400494a38",
	"descriptionMd5": "05cc67e29cc84f9626cfea9a90853973"
}