{
	"raw": {},
	"required": [
		"Filename",
		"Size"
	],
	"package": "nfs-ganesha-nullfs",
	"source": "nfs-ganesha (6.5-8)",
	"version": "6.5-8+b1",
	"section": "libs",
	"priority": "optional",
	"architecture": "amd64",
	"depends": [
		"nfs-ganesha (= 6.5-8+b1)",
		"libc6 (>= 2.4)"
	],
	"installedSize": 78,
	"maintainer": "Christoph Martin <chrism@debian.org>",
	"description": "nfs-ganesha fsal nullfs libraries",
	"homepage": "https://github.com/nfs-ganesha/nfs-ganesha",
	"filename": "pool/main/n/nfs-ganesha/nfs-ganesha-nullfs_6.5-8+b1_amd64.deb",
	"size": 16764,
	"md5": "24885529bb0670e41e685555196d8f8e",
	"sha256": "e766d4920e901a4a14ad27a31cf6ffe0ac47b6ca1db35eb6e609a7dd31af4ab2",
	"descriptionMd5": "8eec76d4f94c5d9c631c35262464c046"
}