{
	"raw": {},
	"required": [
		"Filename",
		"Size"
	],
	"package": "postgresql-all",
	"source": "postgresql-common",
	"version": "278",
	"section": "database",
	"priority": "optional",
	"architecture": "all",
	"depends": [
		"libecpg-dev",
		"libpq-dev",
		"postgresql-common (= 278)",
		"postgresql-server-dev-all",
		"postgresql-17",
		"postgresql-plperl-17",
		"postgresql-plpython3-17",
		"postgresql-pltcl-17"
	],
	"installedSize": 19,
	"maintainer": "Debian PostgreSQL Maintainers <team+postgresql@tracker.debian.org>",
	"description": "metapackage depending on all PostgreSQL server packages",
	"filename": "pool/main/p/postgresql-common/postgresql-all_278_all.deb",
	"size": 14032,
	"md5": "967d37d1dd0c8332b579046002050a1e",
	"sha256": "374a4be75c2f6a591dbeab650e2f91bce934a56add9b5a45ddf734a125af40d8",
	"descriptionMd5": "9a0aaba975f82ef14ff2e821d8683975"
}