{
	"raw": {},
	"required": [
		"Filename",
		"Size"
	],
	"package": "cdecl",
	"version": "2.5-16",
	"section": "devel",
	"priority": "optional",
	"architecture": "amd64",
	"depends": [
		"libc6 (>= 2.34)",
		"libreadline8t64 (>= 6.0)"
	],
	"installedSize": 78,
	"maintainer": "Debian QA Group <packages@qa.debian.org>",
	"description": "Turn English phrases to C or C++ declarations",
	"filename": "pool/main/c/cdecl/cdecl_2.5-16_amd64.deb",
	"size": 27228,
	"md5": "cca020e88cc647680fc42c8dfac857ee",
	"sha256": "f3daa72c5a4ca3d4e562b2af63797f456ea518141a5b3f4254c28f78fc3889e1",
	"descriptionMd5": "4c77c035a2a07fa8fa3ff98ce2990d72"
}