{
	"raw": {},
	"required": [
		"Filename",
		"Size"
	],
	"package": "education-primaryschool",
	"source": "debian-edu",
	"version": "2.13.5",
	"section": "metapackages",
	"priority": "optional",
	"architecture": "amd64",
	"depends": [
		"education-tasks (= 2.13.5)"
	],
	"recommends": [
		"basket",
		"education-menus",
		"gcompris-qt",
		"glpeces",
		"kalgebra",
		"kalzium",
		"kanagram",
		"kbruch",
		"kgeography",
		"khangman",
		"kig",
		"klettres",
		"kmplot",
		"kstars",
		"ktouch",
		"ktuberling",
		"kturtle",
		"kwordquiz",
		"marble",
		"parley",
		"pysiogame",
		"qabcs",
		"ri-li",
		"step",
		"tuxmath",
		"tuxpaint",
		"tuxtype",
		"ulcc"
	],
	"installedSize": 31,
	"maintainer": "Debian Edu Developers <debian-edu@lists.debian.org>",
	"description": "Debian Edu applications for primary school level",
	"homepage": "https://blends.debian.org/edu",
	"filename": "pool/main/d/debian-edu/education-primaryschool_2.13.5_amd64.deb",
	"size": 12088,
	"md5": "5b0c6a443f1292e95ed90b8581fb8759",
	"sha256": "5c9a635bf181d8c272777ab8ef682cf44e3830e34bba8acfbc9d86c39b964375",
	"descriptionMd5": "899165bb2042a2be05dab7db8959194d"
}