{
	"raw": {},
	"required": [
		"Filename",
		"Size"
	],
	"package": "embree-tools",
	"source": "embree",
	"version": "4.3.3+dfsg-1",
	"section": "graphics",
	"priority": "optional",
	"architecture": "amd64",
	"depends": [
		"libc6 (>= 2.38)",
		"libembree4-4 (>= 4.3.3+dfsg)",
		"libgcc-s1 (>= 3.0)",
		"libglfw3 (>= 3.3)",
		"libopengl0",
		"libstdc++6 (>= 14)",
		"libtbb12 (>= 2021.4.0)"
	],
	"installedSize": 136937,
	"maintainer": "Debian Multimedia Maintainers <debian-multimedia@lists.debian.org>",
	"description": "High Performance Ray Tracing Kernels - tools",
	"homepage": "https://embree.github.io/",
	"filename": "pool/main/e/embree/embree-tools_4.3.3+dfsg-1_amd64.deb",
	"size": 20985424,
	"md5": "ce528d928c5b7041ec373a3a25e1ad58",
	"sha256": "bcbc9145915350f492f525994df21175d0009ec04742ac045f77abc56fa7dcb7",
	"descriptionMd5": "13a19ece1c1613f03b3dbaa642c3e5c8"
}