{
	"raw": {},
	"required": [
		"Filename",
		"Size"
	],
	"package": "gcc-12-multilib",
	"source": "gcc-12",
	"version": "12.5.0-8",
	"section": "devel",
	"priority": "optional",
	"architecture": "amd64",
	"depends": [
		"gcc-12-base (= 12.5.0-8)",
		"gcc-12 (= 12.5.0-8)",
		"libc6-dev-i386 (>= 2.23-1~)",
		"libc6-dev-x32 (>= 2.23-1~)",
		"lib32gcc-12-dev (= 12.5.0-8)",
		"libx32gcc-12-dev (= 12.5.0-8)"
	],
	"installedSize": 6,
	"maintainer": "Debian GCC Maintainers <debian-gcc@lists.debian.org>",
	"description": "GNU C compiler (multilib support)",
	"homepage": "http://gcc.gnu.org/",
	"filename": "pool/main/g/gcc-12/gcc-12-multilib_12.5.0-8_amd64.deb",
	"size": 1020,
	"md5": "fce28911d3e9db75b5e60af63b0200dc",
	"sha256": "145fc15d7d636f8aba7aabc23d2a254a930f3fd51d17fcfcd04e3d7c100a5a7a",
	"descriptionMd5": "d1bddfa375b62324197c575c04fb2e4e"
}