{
	"raw": {},
	"required": [
		"Filename",
		"Size"
	],
	"package": "latex-cjk-all",
	"source": "cjk",
	"version": "4.8.5-2",
	"section": "tex",
	"priority": "optional",
	"architecture": "all",
	"depends": [
		"latex-cjk-common (>= 4.8.5-2)",
		"latex-cjk-chinese (>= 4.8.5-2)",
		"latex-cjk-japanese (>= 4.8.5-2)",
		"latex-cjk-korean (= 4.8.5-2)",
		"latex-cjk-thai (= 4.8.5-2)",
		"latex-cjk-chinese-arphic-bsmi00lp",
		"latex-cjk-chinese-arphic-bkai00mp",
		"latex-cjk-chinese-arphic-gbsn00lp",
		"latex-cjk-chinese-arphic-gkai00mp",
		"latex-cjk-japanese-wadalab",
		"fonts-arphic-uming"
	],
	"installedSize": 6,
	"maintainer": "Debian TeX Task Force <debian-tex-maint@lists.debian.org>",
	"description": "installs all LaTeX CJK packages",
	"homepage": "https://www.nongnu.org/cjk",
	"filename": "pool/main/c/cjk/latex-cjk-all_4.8.5-2_all.deb",
	"size": 1052,
	"md5": "0182d048fe461352c12d41a593f4e112",
	"sha256": "2fe98f5ff3b57d411ab4b93947035fff17de53b753a6b67a8f7102ea3e2d3fdc",
	"descriptionMd5": "71fee6ce053b845b35ae5d2f2879314e"
}