{
	"raw": {},
	"required": [
		"Filename",
		"Size"
	],
	"package": "libpod-pom-perl",
	"version": "2.01-4",
	"section": "perl",
	"priority": "optional",
	"architecture": "all",
	"depends": [
		"perl:any"
	],
	"installedSize": 202,
	"maintainer": "Debian Perl Group <pkg-perl-maintainers@lists.alioth.debian.org>",
	"description": "module providing a Pod Object Model",
	"homepage": "https://metacpan.org/release/Pod-POM",
	"filename": "pool/main/libp/libpod-pom-perl/libpod-pom-perl_2.01-4_all.deb",
	"size": 65016,
	"md5": "47b7a9d0def878994aafb199cf68da1f",
	"sha256": "76ece591905bf5de6b814be5045bd77eec5e6a74293a71d6e977b699a96805bf",
	"descriptionMd5": "5fc68269056bf4696a3244f764e0ee8c"
}