{
	"raw": {},
	"required": [
		"Filename",
		"Size"
	],
	"package": "memtool",
	"version": "2018.03.0-1",
	"section": "devel",
	"priority": "optional",
	"architecture": "amd64",
	"depends": [
		"libc6 (>= 2.4)"
	],
	"installedSize": 32,
	"maintainer": "Uwe Kleine-König <ukleinek@debian.org>",
	"description": "Development tool to modify memory mapped registers",
	"homepage": "http://www.pengutronix.de/software/memtool/index_en.html",
	"filename": "pool/main/m/memtool/memtool_2018.03.0-1_amd64.deb",
	"size": 10020,
	"md5": "7d2f88c5d257291411d8c68e9f76a9ac",
	"sha256": "08a621aede5f5b5a1d618bb3c9d3db1bce1823fad86911e7ffd776f19be45da3",
	"descriptionMd5": "0b36cca17a5125d222f764398818ee8a"
}