{
	"raw": {},
	"required": [
		"Filename",
		"Size"
	],
	"package": "rebar3",
	"version": "3.27.0-3",
	"section": "devel",
	"priority": "optional",
	"architecture": "all",
	"depends": [
		"erlang-asn1:any",
		"erlang-base:any (>= 1:27)",
		"erlang-common-test:any",
		"erlang-crypto:any",
		"erlang-dev:any",
		"erlang-dialyzer:any",
		"erlang-edoc:any",
		"erlang-eunit:any",
		"erlang-inets:any",
		"erlang-parsetools:any",
		"erlang-reltool:any",
		"erlang-syntax-tools:any",
		"erlang-tools:any"
	],
	"recommends": [
		"erlang",
		"git"
	],
	"enhances": [
		"erlang"
	],
	"installedSize": 894,
	"maintainer": "Debian Erlang Packagers <pkg-erlang-devel@lists.alioth.debian.org>",
	"description": "Erlang tool to create, develop, and release Erlang libraries and applications",
	"homepage": "https://www.rebar3.org/",
	"filename": "pool/main/r/rebar3/rebar3_3.27.0-3_all.deb",
	"size": 819520,
	"md5": "59bac0abbc63505f2bcef92df54245b5",
	"sha256": "81b6bcc3e421f9da571384f388014f13bf9d504738425d1d6e42fb88d85ddeb4",
	"descriptionMd5": "b1be88821e5accf8f687c87d65cca82c"
}