{"raw":{},"required":["Filename","Size"],"package":"clang-16-doc","source":"llvm-toolchain-16","version":"1:16.0.6-27","section":"doc","priority":"optional","architecture":"all","depends":["libjs-mathjax"],"installedSize":8106,"maintainer":"LLVM Packaging Team <pkg-llvm-team@lists.alioth.debian.org>","description":"C, C++ and Objective-C compiler - Documentation","homepage":"https://www.llvm.org/","filename":"pool/main/l/llvm-toolchain-16/clang-16-doc_16.0.6-27_all.deb","size":1132012,"md5":"401216b9aff3f5d472aa28206517c3ed","sha256":"2eef4113652295f36f0d2ebe076be0b336834f2c96b6a1739b4656191eeeaf45","descriptionMd5":"6bf5242bfe6f159fd907beb982f2315f"}