[{"raw":{},"required":["Filename","Size"],"package":"groonga-tokenizer-mecab","source":"groonga","version":"14.0.5+dfsg-2","section":"libs","priority":"optional","architecture":"amd64","depends":["libc6 (>= 2.4)","libgroonga0t64 (= 14.0.5+dfsg-2)","libmecab2 (>= 0.996)","mecab-naist-jdic | mecab-jumandic-utf8"],"replaces":["libgroonga-tokenizer-mecab (<< 1.2.0-1)"],"breaks":["libgroonga-tokenizer-mecab (<< 1.2.0-1)"],"installedSize":56,"maintainer":"Kentaro Hayashi <kenhys@xdump.org>","description":"MeCab tokenizer for Groonga","homepage":"https://groonga.org/","filename":"pool/main/g/groonga/groonga-tokenizer-mecab_14.0.5+dfsg-2_amd64.deb","size":16692,"md5":"e81261a457722940fafcab53039440d0","sha256":"d7f04f33a4681ef921a32fd93b663298c530bd4bd5fe4cf505bb6c2f9fd384d2","descriptionMd5":"9b62d73f5ac680f18303fed9e4f9f58b"}]