[{
	"raw": {},
	"required": [
		"Filename",
		"Size"
	],
	"package": "php-symfony-sendinblue-notifier",
	"source": "symfony",
	"version": "6.4.20+dfsg-1",
	"section": "php",
	"priority": "optional",
	"architecture": "all",
	"depends": [
		"php-common",
		"php-symfony-deprecation-contracts",
		"php-symfony-http-client",
		"php-symfony-notifier"
	],
	"installedSize": 63,
	"maintainer": "Debian PHP PEAR Maintainers <pkg-php-pear@lists.alioth.debian.org>",
	"description": "Symfony Sendinblue Notifier Bridge",
	"homepage": "https://symfony.com/doc/6.4/notifier.html",
	"filename": "pool/main/s/symfony/php-symfony-sendinblue-notifier_6.4.20+dfsg-1_all.deb",
	"size": 21020,
	"md5": "2fde52fc3d710b178e05f935ef0d1ef0",
	"sha256": "6dc3275ba900075fc590daef72ba4643e0519da0298a53808c596fc38db044e0",
	"descriptionMd5": "357bba11e5bb186acae8eb7684f3e444"
}]