[{"raw":{},"required":["Filename","Size"],"package":"python-cairocffi-doc","source":"cairocffi","version":"1.7.0-1","section":"doc","priority":"optional","architecture":"all","depends":["libjs-jquery (>= 3.6.0)","libjs-sphinxdoc (>= 7.2.2)","sphinx-rtd-theme-common (>= 2.0.0+dfsg)"],"installedSize":1593,"maintainer":"Debian Python Team <team+python@tracker.debian.org>","description":"cffi-based cairo bindings for Python - Documentation","homepage":"https://doc.courtbouillon.org/cairocffi/","builtUsing":"sphinx (= 7.2.6-7)","filename":"pool/main/c/cairocffi/python-cairocffi-doc_1.7.0-1_all.deb","size":98916,"md5":"43080ee74402ddc3a20aecf835fa8dba","sha256":"5611767cec69dc8842a5c55bc854616e2e8b391bee63d611c368fa81ebfcf6cb","descriptionMd5":"39696228dee918c18dec67a66f00232e"}]