[{
	"raw": {},
	"required": [
		"Filename",
		"Size"
	],
	"package": "thunderbird-l10n-sq",
	"source": "thunderbird",
	"version": "1:140.8.0esr-1~deb13u1",
	"section": "localization",
	"priority": "optional",
	"architecture": "all",
	"depends": [
		"thunderbird (<< 1:140.8.0esr-1~deb13u1.1~)",
		"thunderbird (>= 1:140.8.0esr-1~deb13u1)"
	],
	"installedSize": 643,
	"maintainer": "Carsten Schoenert <c.schoenert@t-online.de>",
	"description": "Albanian language package for Thunderbird",
	"homepage": "https://wiki.mozilla.org/L10n:Teams:sq",
	"filename": "pool/main/t/thunderbird/thunderbird-l10n-sq_140.8.0esr-1~deb13u1_all.deb",
	"size": 499228,
	"md5": "10ec8b7c37b4332db775ab38cf8fae3b",
	"sha256": "6e01881242caee05d14f2ed9f13554a3a354373bb292e2947ecfebf0b8a61f7a",
	"descriptionMd5": "1a37f067e6d6b2ee261cd1e54a473d42"
},{
	"raw": {},
	"required": [
		"Filename",
		"Size"
	],
	"package": "thunderbird-l10n-sq",
	"source": "thunderbird",
	"version": "1:140.9.0esr-1~deb13u1",
	"section": "localization",
	"priority": "optional",
	"architecture": "all",
	"depends": [
		"thunderbird (<< 1:140.9.0esr-1~deb13u1.1~)",
		"thunderbird (>= 1:140.9.0esr-1~deb13u1)"
	],
	"installedSize": 644,
	"maintainer": "Carsten Schoenert <c.schoenert@t-online.de>",
	"description": "Albanian language package for Thunderbird",
	"homepage": "https://wiki.mozilla.org/L10n:Teams:sq",
	"filename": "pool/updates/main/t/thunderbird/thunderbird-l10n-sq_140.9.0esr-1~deb13u1_all.deb",
	"size": 499728,
	"sha256": "28e59fe8836a0489a4ca38bc7933894c3eec5a1bb860b2fc7a5149ce433c5165",
	"descriptionMd5": "1a37f067e6d6b2ee261cd1e54a473d42"
}]