[{"raw":{},"required":["Filename","Size"],"package":"geoip-database","version":"20241014-1~bpo12+1","section":"net","priority":"optional","architecture":"all","recommends":["libgeoip1t64 | libgeoip1"],"installedSize":10177,"maintainer":"Patrick Matthäi <pmatthaei@debian.org>","description":"IP lookup command line tools that use the GeoIP library (country database)","homepage":"https://mailfud.org/geoip-legacy/","filename":"pool/main/g/geoip-database/geoip-database_20241014-1~bpo12+1_all.deb","size":2921080,"sha256":"7794cd48da7cb5c77000fbe325eef3f0f148f66db348abfd026f927ea099ce1e","descriptionMd5":"3bfa5b4c9f973261799fb4d9355f3b6c"},{"raw":{},"required":["Filename","Size"],"package":"geoip-database","version":"20230203-1","section":"net","priority":"optional","architecture":"all","recommends":["libgeoip1"],"installedSize":7904,"maintainer":"Patrick Matthäi <pmatthaei@debian.org>","description":"IP lookup command line tools that use the GeoIP library (country database)","homepage":"https://mailfud.org/geoip-legacy/","filename":"pool/main/g/geoip-database/geoip-database_20230203-1_all.deb","size":2221668,"md5":"5745c710f5ebb7e4c9dcfecca5fa90ca","sha256":"506dc723f1ac0f5f9e1de6b0df8c0f9721bb58bce253d21040efadd0f25f01f7","descriptionMd5":"3bfa5b4c9f973261799fb4d9355f3b6c"}]