[{"raw":{},"required":["Filename","Size"],"package":"libghc-tasty-doc","source":"haskell-tasty","version":"1.4.2.3-1","section":"doc","priority":"optional","architecture":"all","depends":["sgml-base (>= 1.28)","haddock-interface-38"],"recommends":["ghc-doc","libghc-ansi-terminal-doc","libghc-optparse-applicative-doc","libghc-tagged-doc","libghc-tasty-dev","libjs-mathjax"],"suggests":["libghc-tasty-prof"],"installedSize":2864,"maintainer":"Debian Haskell Group <pkg-haskell-maintainers@lists.alioth.debian.org>","description":"Haskell testing framework; documentation","homepage":"https://github.com/UnkindPartition/tasty","filename":"pool/main/h/haskell-tasty/libghc-tasty-doc_1.4.2.3-1_all.deb","size":184336,"md5":"3344ab6b4f30502754ba482627359cf4","sha256":"8df39a2915923d7f03c8a5d5886dd3454a03b6d788b391c68686b1b584e08754","descriptionMd5":"a403b1dbe3e1faac91c71eabc340a04e"}]