{"raw":{},"required":["Filename","Size"],"package":"libghc-casa-client-doc","source":"haskell-casa-client","version":"0.0.1-3","section":"doc","priority":"optional","architecture":"all","depends":["haddock-interface-38","sgml-base (>= 1.28)"],"recommends":["ghc-doc","libghc-aeson-doc","libghc-casa-client-dev","libghc-casa-types-doc","libghc-conduit-doc","libghc-conduit-extra-doc","libghc-http-types-doc","libghc-unordered-containers-doc","libjs-mathjax"],"suggests":["libghc-casa-client-prof"],"installedSize":273,"maintainer":"Debian Haskell Group <pkg-haskell-maintainers@lists.alioth.debian.org>","description":"Client for Casa; documentation","homepage":"https://hackage.haskell.org/package/casa-client","filename":"pool/main/h/haskell-casa-client/libghc-casa-client-doc_0.0.1-3_all.deb","size":49652,"md5":"571ba715983125818eb5b57e420c2a92","sha256":"90e1282ee2a6f551a46ab3f253f1d88ec9be80538ed1d978684ff0b58dcbd247","descriptionMd5":"2d38777d8f394d161b8efec991afa74b"}