[{"raw":{},"required":["Filename","Size"],"package":"menu","version":"2.1.49","section":"admin","priority":"optional","architecture":"amd64","depends":["libc6 (>= 2.33)","libgcc-s1 (>= 3.0)","libstdc++6 (>= 11)"],"suggests":["menu-l10n","gksu | kde-cli-tools | ktsuss"],"installedSize":1493,"maintainer":"Bill Allombert <ballombe@debian.org>","description":"generates programs menu for all menu-aware applications","filename":"pool/main/m/menu/menu_2.1.49_amd64.deb","size":371148,"md5":"e22226c5db0480acda03bd0d4bc2b902","sha256":"f27458cf298533e6d5f2dfe77e3c477e9956b25c84163d0cfa0fcc8add3e5b68","descriptionMd5":"0145fb4173b2e75d0c60cc61c6089403"}]