{"raw":{},"required":["Filename","Size"],"package":"linux-source-6.1","source":"linux","version":"6.1.76-1","section":"kernel","priority":"optional","architecture":"all","depends":["binutils","xz-utils"],"recommends":["build-essential","bc","rsync","kmod","cpio","bison","flex","libelf-dev","libssl-dev","linux-config-6.1"],"suggests":["libncurses-dev | ncurses-dev","qtbase5-dev","pkg-config"],"installedSize":135101,"maintainer":"Debian Kernel Team <debian-kernel@lists.debian.org>","description":"Linux kernel source for version 6.1 with Debian patches","homepage":"https://www.kernel.org/","filename":"pool/main/l/linux/linux-source-6.1_6.1.76-1_all.deb","size":138339156,"md5":"97d4a06842c13f675083c6193365193a","sha256":"dea220601d27081efd95c723f1b6120c57459ffd0a0321407005e101c0dd2c24","descriptionMd5":"d43d23de60e09bde0da59cf504ca703d"}