[{"raw":{},"required":["Filename","Size"],"package":"libambix-utils","source":"libambix","version":"0.1.1-2","section":"sound","priority":"optional","architecture":"amd64","depends":["libambix0 (>= 0.1)","libc6 (>= 2.4)","libjack-jackd2-0 (>= 1.9.10+20150825) | libjack-0.125","libsamplerate0 (>= 0.1.7)","libsndfile1 (>= 1.0.20)"],"installedSize":141,"maintainer":"Debian Multimedia Maintainers <debian-multimedia@lists.debian.org>","description":"AMBIsonics eXchange library (utilities)","homepage":"http://ambisonics.iem.at/xchange/format","filename":"pool/main/liba/libambix/libambix-utils_0.1.1-2_amd64.deb","size":43328,"md5":"b012b8d827ad4b58d12f5551d81ae238","sha256":"fba60c1c774a82719d2a92cc6441fda02954782c5f0df8aec555a1f5d398accd","descriptionMd5":"8b3a77261213b228d3c75c78540ebc4f"}]