{"raw":{},"required":["Filename","Size"],"package":"freefem++","source":"freefem++ (4.14+dfsg-1)","version":"4.14+dfsg-1+b2","section":"math","priority":"optional","architecture":"amd64","depends":["libarpack2t64 (>= 2.1)","libc6 (>= 2.38)","libcholmod5 (>= 1:7.3.1)","libgcc-s1 (>= 4.0)","libgl1","libglu1-mesa | libglu1","libglut3.12 (>= 3.4.0)","libhdf5-103-1t64","libopenmpi3t64 (>= 4.1.6)","libscalapack-openmpi2.2 (>= 2.2.1)","libstdc++6 (>= 14)","libumfpack6 (>= 1:7.0.1)"],"installedSize":40768,"maintainer":"Debian Science Maintainers <debian-science-maintainers@lists.alioth.debian.org>","description":"Provides the binaries of the FreeFem++ FE suite","homepage":"http://www.freefem.org/ff++/","filename":"pool/main/f/freefem++/freefem++_4.14+dfsg-1+b2_amd64.deb","size":7935732,"md5":"1d35867f8492d2d2d36ab2a8d7a2d4ac","sha256":"a1a526f563fa4d47a954cba4bbce1f4922c5d4edec4ddf4eb745721e6e64be67","descriptionMd5":"01429493488c740a6366ff810a1828dd"}