{
	"raw": {},
	"required": [
		"Filename",
		"Size"
	],
	"package": "libjsonrpccpp-common0t64",
	"source": "libjson-rpc-cpp (0.7.0-2.2)",
	"version": "0.7.0-2.2+b2",
	"section": "libs",
	"priority": "optional",
	"architecture": "amd64",
	"depends": [
		"libc6 (>= 2.14)",
		"libgcc-s1 (>= 3.0)",
		"libjsoncpp26 (>= 1.9.6)",
		"libstdc++6 (>= 13.1)"
	],
	"suggests": [
		"libjsonrpccpp-client0t64 (= 0.7.0-2.2+b2)",
		"libjsonrpccpp-server0t64 (= 0.7.0-2.2+b2)",
		"libjsonrpccpp-tools (= 0.7.0-2.2+b2)"
	],
	"replaces": [
		"libjsonrpccpp-common0"
	],
	"breaks": [
		"libjsonrpccpp-common0 (<< 0.7.0-2.2)"
	],
	"installedSize": 92,
	"maintainer": "Peter Spiess-Knafl <dev@spiessknafl.at>",
	"description": "common functionality for server and client library",
	"homepage": "https://github.com/cinemast/libjson-rpc-cpp",
	"filename": "pool/main/libj/libjson-rpc-cpp/libjsonrpccpp-common0t64_0.7.0-2.2+b2_amd64.deb",
	"size": 28236,
	"md5": "050b200ab8ceab2b5bb096f827f8d8ee",
	"sha256": "e81aee48c45295e0aee5e5877c3876414c0fa287c00b174be5cae3ee191f0f6e",
	"descriptionMd5": "b35af2e62de15a3bbe188c77ab736883"
}