{
	"raw": {},
	"required": [
		"Filename",
		"Size"
	],
	"package": "libkf5newstuff-data",
	"source": "knewstuff",
	"version": "5.116.0-2",
	"section": "libs",
	"priority": "optional",
	"architecture": "all",
	"installedSize": 2535,
	"maintainer": "Debian Qt/KDE Maintainers <debian-qt-kde@lists.debian.org>",
	"description": "Support for downloading application assets from the network.",
	"homepage": "https://invent.kde.org/frameworks/knewstuff",
	"filename": "pool/main/k/knewstuff/libkf5newstuff-data_5.116.0-2_all.deb",
	"size": 395668,
	"md5": "bf74473f83500c6ba7ff9c48dd107082",
	"sha256": "d680ca0093d300ecedfba35201856fa809bb6d12f386646630c40dd72bef719b",
	"descriptionMd5": "949ba4f6bfaf7622f217987f82d6a09b"
}