{"raw":{},"required":["Filename","Size"],"package":"liblsan0-arm64-cross","source":"gcc-14-cross (7)","version":"14.2.0-6cross1","section":"devel","priority":"optional","architecture":"all","depends":["gcc-14-cross-base (>= 14.2.0-6)","libc6-arm64-cross (>= 2.40)","libgcc-s1-arm64-cross (>= 3.3)"],"installedSize":1003,"maintainer":"Debian GCC Maintainers <debian-gcc@lists.debian.org>","description":"LeakSanitizer -- a memory leak detector (runtime)","homepage":"http://gcc.gnu.org/","builtUsing":"gcc-14 (= 14.2.0-6)","filename":"pool/main/g/gcc-14-cross/liblsan0-arm64-cross_14.2.0-6cross1_all.deb","size":201276,"md5":"17e403b38a9e874de114359ff4047af1","sha256":"54b1814c3d6a063f7ec2ff5078945075ecf8fc0b87ffdd4869f728db2637a3e2","descriptionMd5":"fd77936d8cda7d6af8bc33d6f395c678"}