{"raw":{},"required":["Filename","Size"],"package":"thunderbird-l10n-gd","source":"thunderbird","version":"1:128.3.2esr-1","section":"localization","priority":"optional","architecture":"all","depends":["thunderbird (<< 1:128.3.2esr-1.1~)","thunderbird (>= 1:128.3.2esr-1)"],"recommends":["hunspell-gd | myspell-gd"],"installedSize":857,"maintainer":"Carsten Schoenert <c.schoenert@t-online.de>","description":"Gaelic (Scottish) language package for Thunderbird","homepage":"https://wiki.mozilla.org/L10n:Teams:gd","filename":"pool/main/t/thunderbird/thunderbird-l10n-gd_128.3.2esr-1_all.deb","size":711288,"md5":"79ec8c99910ccd8d79d29d7d360a98de","sha256":"592b730c8aa84328bcd0838d851616fcd9c0e704fe8cb992db9b1959119ee133","descriptionMd5":"f89dbc586dc8f1005ae395c073cd1a24"}