[{
	"raw": {},
	"required": [
		"Filename",
		"Size"
	],
	"package": "gap-grape",
	"version": "4.9.3+ds-1",
	"section": "math",
	"priority": "optional",
	"architecture": "all",
	"depends": [
		"gap (>= 4.13.0)",
		"gap-primgrp",
		"nauty"
	],
	"recommends": [
		"bliss"
	],
	"suggests": [
		"pdf-viewer",
		"www-browser"
	],
	"installedSize": 747,
	"maintainer": "Debian Science Maintainers <debian-science-maintainers@lists.alioth.debian.org>",
	"description": "GRaph Algorithms using PErmutation groups for GAP",
	"homepage": "https://www.gap-system.org/Packages/grape.html",
	"filename": "pool/main/g/gap-grape/gap-grape_4.9.3+ds-1_all.deb",
	"size": 341904,
	"md5": "da02f8eb55adc48a606aee53280274c4",
	"sha256": "3a2ec56a576312fc964b32bdfdbc4b9823207cbef20b131eacccf47646a9e9f6",
	"descriptionMd5": "701b210ec4d52136ba2de99550b30d51"
}]