[{
	"raw": {},
	"required": [
		"Filename",
		"Size"
	],
	"package": "gltfpack",
	"source": "meshoptimizer (0.22+dfsg-1)",
	"version": "0.22+dfsg-1+b1",
	"section": "graphics",
	"priority": "optional",
	"architecture": "amd64",
	"depends": [
		"libc6 (>= 2.38)",
		"libgcc-s1 (>= 3.0)",
		"libmeshoptimizer2d (>= 0.21+dfsg)",
		"libstdc++6 (>= 11)"
	],
	"installedSize": 307,
	"maintainer": "Timo Röhling <roehling@debian.org>",
	"description": "glTF mesh file optimizer",
	"homepage": "https://github.com/zeux/meshoptimizer",
	"filename": "pool/main/m/meshoptimizer/gltfpack_0.22+dfsg-1+b1_amd64.deb",
	"size": 123080,
	"md5": "f53939f47f9bd6678adbec55d9625651",
	"sha256": "bf167fd87686a2f2b90d1edec24c8f04a306167b43e23d99651d3a8adc62190f",
	"descriptionMd5": "8d950db402c66032f196ed5330361e61"
}]