[{
	"raw": {},
	"required": [
		"Filename",
		"Size"
	],
	"package": "libtlsh4",
	"source": "tlsh",
	"version": "4.12.0+ds-2",
	"section": "libs",
	"priority": "optional",
	"architecture": "amd64",
	"depends": [
		"libc6 (>= 2.38)",
		"libgcc-s1 (>= 3.0)",
		"libstdc++6 (>= 5)"
	],
	"installedSize": 126,
	"maintainer": "Debian Security Tools <team+pkg-security@tracker.debian.org>",
	"description": "fuzzy hashing library",
	"homepage": "https://github.com/trendmicro/tlsh",
	"filename": "pool/main/t/tlsh/libtlsh4_4.12.0+ds-2_amd64.deb",
	"size": 22360,
	"md5": "5a05a44d4c1aefd5b3d8215d3f13b744",
	"sha256": "cf60dc4fd1cf24a74df60a3a5256a8ca3a702242021ac9a7ea320401e150eafd",
	"descriptionMd5": "968346b17fb7378f7f65a4541740ae69"
}]