[{
	"raw": {},
	"required": [
		"Filename",
		"Size"
	],
	"package": "libvisp-tt-mi3.6t64",
	"source": "visp (3.6.0-5)",
	"version": "3.6.0-5+b1",
	"section": "libs",
	"priority": "optional",
	"architecture": "amd64",
	"depends": [
		"libc6 (>= 2.29)",
		"libgcc-s1 (>= 3.0)",
		"libgomp1 (>= 4.9)",
		"libstdc++6 (>= 13.1)",
		"libvisp-core3.6t64 (>= 3.6.0)",
		"libvisp-tt3.6t64 (= 3.6.0-5+b1)"
	],
	"replaces": [
		"libvisp-tt-mi3.6"
	],
	"breaks": [
		"libvisp-tt-mi3.6 (<< 3.6.0-5)"
	],
	"installedSize": 192,
	"maintainer": "Debian Science Maintainers <debian-science-maintainers@lists.alioth.debian.org>",
	"description": "visual servoing platform tt-mi library",
	"homepage": "https://visp.inria.fr",
	"filename": "pool/main/v/visp/libvisp-tt-mi3.6t64_3.6.0-5+b1_amd64.deb",
	"size": 82800,
	"md5": "4f88937b35a26b9ad06a17ff048df5eb",
	"sha256": "33fd7e47d37fa95cab22e9fa3153e6a5190bd8520f4987e2bc41ee279ab22856",
	"descriptionMd5": "5620302e25a04185404cf8f6d2a17fd0"
}]