[{
	"raw": {},
	"required": [
		"Filename",
		"Size"
	],
	"package": "rust-gdb",
	"source": "rustc",
	"version": "1.94.1+dfsg1-1",
	"section": "rust",
	"priority": "optional",
	"architecture": "all",
	"depends": [
		"gdb"
	],
	"suggests": [
		"gdb-doc"
	],
	"replaces": [
		"rustc (<< 1.1.0+dfsg1-1)"
	],
	"installedSize": 418,
	"maintainer": "Debian Rust Maintainers <pkg-rust-maintainers@alioth-lists.debian.net>",
	"description": "Rust debugger (gdb)",
	"homepage": "http://www.rust-lang.org/",
	"filename": "pool/main/r/rustc/rust-gdb_1.94.1+dfsg1-1_all.deb",
	"size": 269224,
	"md5": "bbbd9b94e341bac4919b4fe004ae9b3f",
	"sha256": "169faab6ec7737650c7653bcffbf3d795350aba49bd437b28dffd5c11ac2fc7c",
	"descriptionMd5": "1afbf06d9ee3b7b85a98c81c15ed3109"
}]