[{
	"raw": {},
	"required": [
		"Filename",
		"Size"
	],
	"package": "python3-rq",
	"source": "python-rq",
	"version": "2.8-1",
	"section": "python",
	"priority": "optional",
	"architecture": "all",
	"depends": [
		"python3-click",
		"python3-redis",
		"python3-croniter",
		"python3:any"
	],
	"installedSize": 500,
	"maintainer": "Debian Python Team <team+python@tracker.debian.org>",
	"description": "Simple job queues for Python 3",
	"homepage": "https://github.com/rq/rq",
	"filename": "pool/main/p/python-rq/python3-rq_2.8-1_all.deb",
	"size": 102748,
	"md5": "628577140dd678e6c6a1f5249926f858",
	"sha256": "6c02ab526648cf6a6f28ec6062edf6e9786831e35344551003c5475c8c49b17d",
	"descriptionMd5": "d192cb8bf5b9d82429bd09323c51ebe9"
}]